KEL/__init__.py
KEL/test.py
KEL/Assets/__init__.py
KEL/Engine/__init__.py
KEL/Engine/Components/__init__.py
KEL/Engine/Components/collideComp.py
KEL/Engine/Components/collidePolyComp.py
KEL/Engine/Components/gravityComp.py
KEL/Engine/Components/renderPolyComp.py
KEL/Engine/Components/renderRectComp.py
KEL/Engine/Components/transformPolyComp.py
KEL/Engine/Components/transformRectComp.py
KEL/Engine/Core/__init__.py
KEL/Engine/Core/core.py
KEL/Engine/Core/event.py
KEL/Engine/Core/filePreset.py
KEL/Engine/Core/screen.py
KEL/Engine/Game/__init__.py
KEL/Engine/Game/run.py
KEL/Engine/Maths/__init__.py
KEL/Engine/Maths/maths.py
KEL/Engine/Models/__init__.py
KEL/Engine/Models/emptyModel.py
KEL/Engine/Setup/__init__.py
KEL/Engine/Setup/pygameSetup.py
KEL/UI/__init__.py
KEL_GameEngine-0.0.12.2.dist-info/METADATA
KEL_GameEngine-0.0.12.2.dist-info/WHEEL
KEL_GameEngine-0.0.12.2.dist-info/top_level.txt
KEL_GameEngine-0.0.12.2.dist-info/RECORD
